pytest_bdd_web.py
pytest_bdd_web-0.1.1.dist-info/LICENSE
pytest_bdd_web-0.1.1.dist-info/METADATA
pytest_bdd_web-0.1.1.dist-info/WHEEL
pytest_bdd_web-0.1.1.dist-info/entry_points.txt
pytest_bdd_web-0.1.1.dist-info/top_level.txt
pytest_bdd_web-0.1.1.dist-info/RECORD
