Metadata-Version: 2.1
Name: pytest-bdd-web
Version: 0.1.1
Summary: A simple plugin to use with pytest
Home-page: https://github.com/mohawk2/pytest-bdd-web
Author: Ed J
Author-email: mohawk2@users.noreply.github.com
Maintainer: Ed J
Maintainer-email: mohawk2@users.noreply.github.com
License: MIT
Platform: UNKNOWN
Classifier: Development Status :: 4 - Beta
Classifier: Framework :: Pytest
Classifier: Intended Audience :: Developers
Classifier: Topic :: Software Development :: Testing
Classifier: Operating System :: OS Independent
Classifier: License :: OSI Approved :: MIT License
Classifier: Programming Language :: Python
Classifier: Programming Language :: Python :: 3
Classifier: Programming Language :: Python :: Implementation :: CPython
Classifier: Programming Language :: Python :: 3.6
Classifier: Programming Language :: Python :: 3.7
Classifier: Programming Language :: Python :: 3.8
Requires-Python: >=3.5
Requires-Dist: pytest (>=3.5.0)
Requires-Dist: pytest-bdd (>=3.2)
Requires-Dist: mechanize (>=0.4.5)
Requires-Dist: pyquery (>=1.4.1)
